sp/__init__.py
sp/admin.py
sp/apps.py
sp/backends.py
sp/models.py
sp/urls.py
sp/utils.py
sp/views.py
sp/migrations/0001_initial.py
sp/migrations/0002_auto_20191205_1758.py
sp/migrations/0003_auto_20200331_1934.py
sp/migrations/0004_auto_20200401_1328.py
sp/migrations/0005_auto_20210323_1526.py
sp/migrations/0006_remove_idp_slug.py
sp/migrations/0007_auto_20210323_1535.py
sp/migrations/0008_auto_20210323_1644.py
sp/migrations/0009_idpuser.py
sp/migrations/0010_auto_20210326_1923.py
sp/migrations/0011_idp_require_attributes.py
sp/migrations/0012_idp_authn_comparison_idp_authn_context.py
sp/migrations/0013_idp_prepare_request_method_idp_update_user_method.py
sp/migrations/0014_alter_idp_options_idp_sort_order.py
sp/migrations/0015_idp_logout_request_signed_idp_logout_response_signed.py
sp/migrations/__init__.py
sp/templates/admin/sp/idp/change_form.html
sp/templates/sp/error.html
sp/templates/sp/test.html
sp/templates/sp/unauth.html
django_saml_sp-0.8.0.dist-info/LICENSE
django_saml_sp-0.8.0.dist-info/METADATA
django_saml_sp-0.8.0.dist-info/WHEEL
django_saml_sp-0.8.0.dist-info/top_level.txt
django_saml_sp-0.8.0.dist-info/RECORD
