Metadata-Version: 2.1
Name: django-saml-sp
Version: 0.8.0
Summary: A Django application for running one or more SAML service providers (SP).
Home-page: https://github.com/imsweb/django-saml-sp
Author: Dan Watson
Author-email: watsond@imsweb.com
License: BSD-3-Clause
Project-URL: Source, https://github.com/imsweb/django-saml-sp
Classifier: Development Status :: 3 - Alpha
Classifier: Environment :: Web Environment
Classifier: Framework :: Django
Classifier: Intended Audience :: Developers
Classifier: License :: OSI Approved :: BSD License
Classifier: Operating System :: OS Independent
Classifier: Programming Language :: Python
Classifier: Programming Language :: Python :: 3
Classifier: Programming Language :: Python :: 3 :: Only
Requires-Python: >=3.6
License-File: LICENSE
Requires-Dist: cryptography
Requires-Dist: python3-saml
